rfb_can_sniffer/__init__.py
rfb_can_sniffer/__version__.py
rfb_can_sniffer/can_sniffer.py
rfb_can_sniffer/context.py
rfb_can_sniffer-0.0.1.dist-info/LICENSE.txt
rfb_can_sniffer-0.0.1.dist-info/METADATA
rfb_can_sniffer-0.0.1.dist-info/WHEEL
rfb_can_sniffer-0.0.1.dist-info/top_level.txt
rfb_can_sniffer-0.0.1.dist-info/RECORD
